slubfind/__init__.py
slubfind/_version.py
slubfind/client.py
slubfind/parser.py
slubfind-0.1.0.dist-info/LICENSE
slubfind-0.1.0.dist-info/METADATA
slubfind-0.1.0.dist-info/WHEEL
slubfind-0.1.0.dist-info/top_level.txt
slubfind-0.1.0.dist-info/RECORD
