Metadata-Version: 2.1
Name: slubfind
Version: 0.1.0
Summary: query data exports from the SLUB catalogue
Author: Donatus Herre
Author-email: donatus.herre@slub-dresden.de
License: GPLv3
Project-URL: homepage, https://github.com/slub/slubfind
Classifier: Programming Language :: Python :: 3
Classifier: Operating System :: OS Independent
Classifier: License :: OSI Approved :: GNU General Public License v3 (GPLv3)
Classifier: Development Status :: 3 - Alpha
Classifier: Intended Audience :: Developers
Classifier: Intended Audience :: Education
Classifier: Intended Audience :: Science/Research
Classifier: Topic :: Software Development :: Libraries :: Python Modules
Requires-Python: >=3.7
License-File: LICENSE
Requires-Dist: txpyfind
